vanillacorn.py
vanillacorn-0.1.2.dist-info/METADATA
vanillacorn-0.1.2.dist-info/WHEEL
vanillacorn-0.1.2.dist-info/entry_points.txt
vanillacorn-0.1.2.dist-info/licenses/LICENSE.txt
vanillacorn-0.1.2.dist-info/RECORD
