Metadata-Version: 2.4
Name: vanillacorn
Version: 0.1.2
Summary: A vanilla ASGI server: a basic implementation of the ASGI specification using pure Python and asyncio.
Author-email: bRuttaZz <agrajpdas@gmail.com>
License-Expression: GPL-3.0
License-File: LICENSE.txt
Keywords: asgi,cli,pure python,server,single file,vanilla
Classifier: Programming Language :: Python :: 3
Classifier: Programming Language :: Python :: 3.9
Classifier: Programming Language :: Python :: 3.10
Classifier: Programming Language :: Python :: 3.11
Classifier: Programming Language :: Python :: 3.12
Classifier: Programming Language :: Python :: 3.13
Classifier: Topic :: Internet :: WWW/HTTP :: HTTP Servers
Classifier: Topic :: Internet :: WWW/HTTP :: WSGI :: Server
Classifier: Topic :: Software Development
Requires-Python: >=3.9
